{
    "notes": [
        {
            "title": "Deep Learning",
            "file": "DeepLearning.pdf",
            "tags": [
                "deep learning",
                "machine learning",
                "artificial intelligence"
            ]
        },
        {
            "title": "Differentiation",
            "file": "Differentiation.pdf",
            "tags": [
                "calculus"
            ]
        },
        {
            "title": "Diffie Hellman Key-Exchange",
            "file": "DiffieHellman.pdf",
            "tags": [
                "cryptography",
                "diffie hellman"
            ]
        },
        {
            "title": "Elliptic Curve Criptography",
            "file": "EllipticCurveCriptography.pdf",
            "tags": [
                "elliptic curve",
                "cryptography",
                "diffie hellman"
            ]
        },
        {
            "title": "Euler\"s Formula",
            "file": "EulerFormula.pdf",
            "tags": [
                "complex analysis",
                "series",
                "trigonometry",
                "euler"
            ]
        },
        {
            "title": "Euler-Mascheroni constant",
            "file": "EulerMascheroni.pdf",
            "tags": [
                "series",
                "euler",
                "mascheroni"
            ]
        },
        {
            "title": "Fundamentals of Quantum Computing",
            "file": "Fundamentals.pdf",
            "tags": [
                "quantum",
                "spin",
                "matrix",
                "vector",
                "linear transformation",
                "probability"
            ]
        },
        {
            "title": "Grover\"s Algorithm",
            "file": "GroversAlgorithm.pdf",
            "tags": [
                "quantum",
                "algorithms",
                "spin",
                "matrices",
                "grover"
            ]
        },
        {
            "title": "Hilbert Space",
            "file": "HilbertSpace.pdf",
            "tags": [
                "vector",
                "matrices",
                "hilbert"
            ]
        },
        {
            "title": "Integration",
            "file": "Integration.pdf",
            "tags": [
                "calculus"
            ]
        },
        {
            "title": "Limits",
            "file": "Limits.pdf",
            "tags": [
                "limit, calculus"
            ]
        },
        {
            "title": "Matrices",
            "file": "Matrices.pdf",
            "tags": [
                "matrices",
                "linear transformation",
                "trigonometry"
            ]
        },
        {
            "title": "Ray-Sphere Intersection",
            "file": "RaySphereIntersection.pdf",
            "tags": [
                "ray tracing",
                "vector"
            ]
        },
        {
            "title": "Riemann Hypothesis",
            "file": "RiemannHypothesis.pdf",
            "tags": [
                "zeta function",
                "complex analysis",
                "series",
                "prime counting function",
                "number theory",
                "riemann",
                "euler"
            ]
        },
        {
            "title": "RSA",
            "file": "RSA.pdf",
            "tags": [
                "cryptography",
                "euler"
            ]
        },
        {
            "title": "Sorting Algorithms",
            "file": "SortingAlgorithms.pdf",
            "tags": [
                "sorting",
                "algorithms"
            ]
        },
        {
            "title": "Taylor Series",
            "file": "TaylorSeries.pdf",
            "tags": [
                "calculus",
                "taylor",
                "series"
            ]
        }
    ]
}